LICENSE
MANIFEST.in
README.rst
setup.cfg
setup.py
versioneer.py
tpDcc/__init__.py
tpDcc/dccs/__init__.py
tpDcc/dccs/maya/__init__.py
tpDcc/dccs/maya/__logging__.ini
tpDcc/dccs/maya/__version__.py
tpDcc/dccs/maya/_version.py
tpDcc/dccs/maya/dcc.py
tpDcc/dccs/maya/loader.py
tpDcc/dccs/maya/api/__init__.py
tpDcc/dccs/maya/api/attributetypes.py
tpDcc/dccs/maya/api/curves.py
tpDcc/dccs/maya/api/exceptions.py
tpDcc/dccs/maya/api/mathlib.py
tpDcc/dccs/maya/api/mesh.py
tpDcc/dccs/maya/api/node.py
tpDcc/dccs/maya/api/plugs.py
tpDcc/dccs/maya/api/skin.py
tpDcc/dccs/maya/api/commands/__init__.py
tpDcc/dccs/maya/api/commands/setskinweights.py
tpDcc/dccs/maya/core/__init__.py
tpDcc/dccs/maya/core/animation.py
tpDcc/dccs/maya/core/attribute.py
tpDcc/dccs/maya/core/blendshape.py
tpDcc/dccs/maya/core/callback.py
tpDcc/dccs/maya/core/camera.py
tpDcc/dccs/maya/core/cluster.py
tpDcc/dccs/maya/core/color.py
tpDcc/dccs/maya/core/colormanagement.py
tpDcc/dccs/maya/core/command.py
tpDcc/dccs/maya/core/common.py
tpDcc/dccs/maya/core/component.py
tpDcc/dccs/maya/core/constants.py
tpDcc/dccs/maya/core/constraint.py
tpDcc/dccs/maya/core/contexts.py
tpDcc/dccs/maya/core/curve.py
tpDcc/dccs/maya/core/decorators.py
tpDcc/dccs/maya/core/deformer.py
tpDcc/dccs/maya/core/directory.py
tpDcc/dccs/maya/core/distance.py
tpDcc/dccs/maya/core/exceptions.py
tpDcc/dccs/maya/core/filtertypes.py
tpDcc/dccs/maya/core/follicle.py
tpDcc/dccs/maya/core/geometry.py
tpDcc/dccs/maya/core/geometrycache.py
tpDcc/dccs/maya/core/gui.py
tpDcc/dccs/maya/core/helpers.py
tpDcc/dccs/maya/core/humanik.py
tpDcc/dccs/maya/core/ik.py
tpDcc/dccs/maya/core/joint.py
tpDcc/dccs/maya/core/layer.py
tpDcc/dccs/maya/core/mash.py
tpDcc/dccs/maya/core/matrix.py
tpDcc/dccs/maya/core/mayapymanager.py
tpDcc/dccs/maya/core/menu.py
tpDcc/dccs/maya/core/mesh.py
tpDcc/dccs/maya/core/modelpanel.py
tpDcc/dccs/maya/core/name.py
tpDcc/dccs/maya/core/namespace.py
tpDcc/dccs/maya/core/ncloth.py
tpDcc/dccs/maya/core/nhair.py
tpDcc_dccs_maya.egg-info/PKG-INFO
tpDcc_dccs_maya.egg-info/SOURCES.txt
tpDcc_dccs_maya.egg-info/dependency_links.txt
tpDcc_dccs_maya.egg-info/not-zip-safe
tpDcc_dccs_maya.egg-info/requires.txt
tpDcc_dccs_maya.egg-info/top_level.txt