Metadata-Version: 2.1
Name: tpDcc-dccs-maya
Version: 0.0.18
Summary: Maya implementation for tpDcc. Utils functions to work with Maya Python APIs.
Home-page: https://github.com/tpDcc/tpDcc-dccs-maya
Author: Tomas Poveda
Author-email: tpovedatd@gmail.com
License: MIT
Platform: UNKNOWN
Provides-Extra: dev
Provides-Extra: test
